[
  {
    "name": "officedev-microsoft-teams-samples-bot-configuration-app-nodejs",
    "source": "officeDev",
    "title": "Bot configuration app with type ahead search control",
    "shortDescription": "Demonstrating the feature of configurable card with type ahead search (static and dynamic) control on Adaptive Cards.",
    "url": "https://github.com/OfficeDev/Microsoft-Teams-Samples/tree/main/samples/bot-configuration-app/nodejs",
    "longDescription": [
      "Demonstrating the feature of configurable card with type ahead search (static and dynamic) control on Adaptive Cards."
    ],
    "creationDateTime": "2023-07-31",
    "updateDateTime": "2023-07-31",
    "products": [
      "Teams"
    ],
    "metadata": [
      {
        "key": "TEAMS-SAMPLE-SOURCE",
        "value": "OfficeDev"
      },
      {
        "key": "TEAMS-SERVER-LANGUAGE",
        "value": "javascript"
      },
      {
        "key": "TEAMS-SERVER-PLATFORM",
        "value": "express"
      },
      {
        "key": "TEAMS-FEATURES",
        "value": "bot"
      }
    ],
    "thumbnails": [
      {
        "type": "image",
        "order": 100,
        "url": "https://raw.githubusercontent.com/OfficeDev/Microsoft-Teams-Samples/main/samples/bot-configuration-app/nodejs/Images/ConfigurationBot.gif",
        "alt": "Solution UX showing typeahead search control in adaptive cards"
      }
    ],
    "authors": [
      {
        "gitHubAccount": "OfficeDev",
        "pictureUrl": "https://avatars.githubusercontent.com/u/6789362?s=200&v=4",
        "name": "OfficeDev"
      }
    ],
    "references": [
      {
        "name": "Teams developer documentation",
        "url": "https://aka.ms/TeamsPlatformDocs"
      },
      {
        "name": "Teams developer questions",
        "url": "https://aka.ms/TeamsPlatformFeedback"
      },
      {
        "name": "Teams development videos from Microsoft",
        "url": "https://aka.ms/sample-ref-teams-vids-from-microsoft"
      },
      {
        "name": "Teams development videos from the community",
        "url": "https://aka.ms/sample-ref-teams-vids-from-community"
      }
    ]
  }
]